LICENSE
README.md
setup.py
bin/car
car/__init__.py
car/car.py
car/resources/car.toml
car/resources/bash_completion.d/car
car/resources/containers/ajp/Dockerfile
car/resources/containers/ajp/README.md
car/resources/containers/ajp/docker-compose.yml
car/resources/containers/ajp/env_info.txt
car/resources/containers/ajp/config/ajp.conf
car/resources/containers/ajp/config/httpd_raw.conf
car/resources/containers/ajp/config/jk_workers.properties
car/resources/containers/ajp/scripts/build_modjk.sh
car/resources/containers/ajp/scripts/start.sh
car/resources/containers/ftp/Dockerfile
car/resources/containers/ftp/README.md
car/resources/containers/ftp/docker-compose.yml
car/resources/containers/ftp/env_info.txt
car/resources/containers/ftp/config/vsftpd.conf
car/resources/containers/ftp/scripts/start.sh
car/resources/containers/h2b/Dockerfile
car/resources/containers/h2b/README.md
car/resources/containers/h2b/docker-compose.yml
car/resources/containers/h2b/env_info.txt
car/resources/containers/h2b/scripts/h2b.py
car/resources/containers/h2b/scripts/start.sh
car/resources/containers/mysql/Dockerfile
car/resources/containers/mysql/README.md
car/resources/containers/mysql/docker-compose.yml
car/resources/containers/mysql/env_info.txt
car/resources/containers/mysql/config/custom.cnf
car/resources/containers/mysql/scripts/init.sql
car/resources/containers/mysql/scripts/start.sh
car/resources/containers/neo4j/Dockerfile
car/resources/containers/neo4j/README.md
car/resources/containers/neo4j/docker-compose.yml
car/resources/containers/neo4j/env_info.txt
car/resources/containers/neo4j/scripts/start.sh
car/resources/containers/nginx/Dockerfile
car/resources/containers/nginx/README.md
car/resources/containers/nginx/docker-compose.yml
car/resources/containers/nginx/env_info.txt
car/resources/containers/nginx/config/default.conf
car/resources/containers/nginx/scripts/start.sh
car/resources/containers/php/Dockerfile
car/resources/containers/php/README.md
container_arsenal.egg-info/PKG-INFO
container_arsenal.egg-info/SOURCES.txt
container_arsenal.egg-info/dependency_links.txt
container_arsenal.egg-info/requires.txt
container_arsenal.egg-info/top_level.txt