Metadata-Version: 2.1
Name: container-arsenal
Version: 2.2.0
Summary: A small arsenal of useful docker containers and a script to easy start, stop and manage them.
Home-page: https://github.com/qtc-de/container-arsenal
Author: Tobias Neitzel (@qtc_de)
Author-email: 
License: UNKNOWN
Platform: UNKNOWN
Classifier: Programming Language :: Python :: 3
Classifier: Operating System :: Unix
Classifier: License :: OSI Approved :: GNU General Public License v3 (GPLv3)
License-File: LICENSE
